vcat/__init__.py
vcat/config.py
vcat/fit_functions.py
vcat/helpers.py
vcat/image_cube.py
vcat/image_data.py
vcat/kinematics.py
vcat/ridgeline.py
vcat/stacking_helpers.py
vcat/plots/__init__.py
vcat/plots/evolution_plot.py
vcat/plots/fits_image.py
vcat/plots/jet_profile_plot.py
vcat/plots/kinematic_plot.py
vcat/plots/model_image_plot.py
vcat/plots/multi_fits_image.py
vcat_vlbi-0.0.0.dist-info/licenses/LICENSE
vcat_vlbi-0.0.0.dist-info/METADATA
vcat_vlbi-0.0.0.dist-info/WHEEL
vcat_vlbi-0.0.0.dist-info/top_level.txt
vcat_vlbi-0.0.0.dist-info/RECORD
