Metadata-Version: 2.4
Name: vcat-vlbi
Version: 0.0.0
Summary: VLBI Comprehensive Analysis Toolkit
Home-page: https://github.com/mpifr-vlbi/VCAT
Author: Anne-Kathrin Baczko, Vieri Bartolini, Florian Eppel, Felix Pötzl, Luca Ricci, Jan Röder, Florian Rösch
Author-email: anne-kathrin.baczko@chalmers.se, vbartolini@mpifr-bonn.mpg.de, florian@eppel.space, luca.ricci@uni-wuerzburg.de, jroeder@mpifr-bonn.mpg.de, florian.roesch@uni-wuerzburg.de
Maintainer: Florian Eppel
Maintainer-email: florian@eppel.space
License: GPLv3
Project-URL: Documentation, https://github.com/mpifr-vlbi/VCAT
Project-URL: Bug Tracker, https://github.com/mpifr-vlbi/VCAT
Keywords: VLBI astronomy analysis radio-astronomy radio agn jets
Classifier: Programming Language :: Python :: 3
Classifier: License :: OSI Approved :: GNU General Public License v3 (GPLv3)
Classifier: Operating System :: OS Independent
Requires-Python: >=3.6
License-File: LICENSE
Requires-Dist: numpy>=1.24
Requires-Dist: pandas>=2.1
Requires-Dist: astropy>=6.0
Requires-Dist: scipy>=1.11
Requires-Dist: matplotlib>=3.7
Requires-Dist: scikit-image>=0.20.0
Requires-Dist: sympy>=1.12
Requires-Dist: pexpect>=4.8
Requires-Dist: astroquery>=0.4.6
Requires-Dist: tqdm>=4.66
Requires-Dist: colormaps>=0.1
Dynamic: author
Dynamic: author-email
Dynamic: classifier
Dynamic: description
Dynamic: description-content-type
Dynamic: home-page
Dynamic: keywords
Dynamic: license
Dynamic: license-file
Dynamic: maintainer
Dynamic: maintainer-email
Dynamic: project-url
Dynamic: requires-dist
Dynamic: requires-python
Dynamic: summary
